public_dropbox_urls
