Metadata-Version: 1.0
Name: public-dropbox-urls
Version: 0.0.0.4
Summary: Find Dropbox download url from a file's sharing url
Home-page: https://github.com/bepetersn/public-dropbox-urls/
Author: Brian Peterson
Author-email: bepetersn@gmail.com
License: MIT
Platform: UNKNOWN
